panel_siemens_ix/__init__.py
panel_siemens_ix/colors.py
panel_siemens_ix/py.typed
panel_siemens_ix/theme.py
panel_siemens_ix/static/black-logo.jpg
panel_siemens_ix/static/black-logo.svg
panel_siemens_ix/static/sie-favicon_intranet.ico
panel_siemens_ix/static/sie-logo-black-rgb.svg
panel_siemens_ix/static/sie-logo-black-rgb_org.svg
panel_siemens_ix/static/sie-logo-petrol-rgb.svg
panel_siemens_ix/static/sie-logo-petrol-rgb_org.svg
panel_siemens_ix/static/sie-logo-white-rgb.svg
panel_siemens_ix/static/sie-logo-white-rgb_org.svg
panel_siemens_ix/static/whilte-logo.jpg
panel_siemens_ix/static/white-logo.svg
panel_siemens_ix-0.3.0.dist-info/METADATA
panel_siemens_ix-0.3.0.dist-info/WHEEL
panel_siemens_ix-0.3.0.dist-info/RECORD
