Metadata-Version: 2.4
Name: panel-siemens-ix
Version: 0.3.0
Summary: Add your description here
Author-email: legout <ligno.blades@gmail.com>
Requires-Python: >=3.13
Requires-Dist: panel-material-ui>=0.3.3
Requires-Dist: panel>=1.7.4
Provides-Extra: examples
Requires-Dist: altair>=5.5.0; extra == 'examples'
Requires-Dist: duckdb>=1.3.2; extra == 'examples'
Requires-Dist: hvplot>=0.11.3; extra == 'examples'
Requires-Dist: plotly>=6.2.0; extra == 'examples'
Requires-Dist: vegafusion>=2.0.2; extra == 'examples'
Requires-Dist: vl-convert-python>=1.8.0; extra == 'examples'
